{
  "abuse_words": [
    { "ml": "പോഡാ", "ml_en": "poda" },
    { "ml": "പൊന്നീ", "ml_en": "ponni" },
    { "ml": "തല്ലു വാങ്ങ്", "ml_en": "thallu vaang" },
    { "ml": "തെറ്റൻ", "ml_en": "thettan" },
    { "ml": "കുഴപ്പക്കാരൻ", "ml_en": "kuzhappakkaran" },
    { "ml": "പെണ്ണാട്ടൻ", "ml_en": "pennaattan" },
    { "ml": "മക്കളെ ഇല്ലാത്തവൻ", "ml_en": "makkale illathavan" },
    { "ml": "താരളന്‍", "ml_en": "thaaralan" },
    { "ml": "ചോദ്യക്കാരൻ", "ml_en": "chodyakkaran" },
    { "ml": "കള്ളൻ", "ml_en": "kallan" },
    { "ml": "നൈസ് നായ്", "ml_en": "nais naayi" },
    { "ml": "തവള", "ml_en": "thavala" },
    { "ml": "മണ്ടൻ", "ml_en": "mandan" },
    { "ml": "കുഴപ്പമുള്ളവൻ", "ml_en": "kuzhappam ullavan" },
    { "ml": "തരംതാഴ്ന്നവൻ", "ml_en": "tharam thazhnavan" },
    { "ml": "വള്ള്യ പണി", "ml_en": "valliya pani" },
    { "ml": "തല്ലാൻ പോകൂ", "ml_en": "thallaan poku" },
    { "ml": "പോവെട്ട", "ml_en": "povetta" },
    { "ml": "നിന്റെ അമ്മയെ...", "ml_en": "ninte ammaye..." },
    { "ml": "നിന്റെ ചേച്ചിയെ...", "ml_en": "ninte chechhiye..." }
  ]
}
